{
	"fields": [
        {
            "topic_message_name": "ev3_sensor",
            "topic_type_name": "Ev3PduSensor",
            "sub": false
        },
        {
            "topic_message_name": "ev3_actuator",
            "topic_type_name": "Ev3PduActuator",
            "sub": true
        },
        {
            "topic_message_name": "scan",
            "topic_type_name": "LaserScan",
            "sub": false
        },
        {
            "topic_message_name": "imu",
            "topic_type_name": "Imu",
            "sub": false
        },
        {
            "topic_message_name": "cmd_vel",
            "topic_type_name": "Twist",
            "sub": true
        }
	]
}
